vanitymnem.py
VanityMnem-0.0.2.dist-info/LICENSE
VanityMnem-0.0.2.dist-info/METADATA
VanityMnem-0.0.2.dist-info/WHEEL
VanityMnem-0.0.2.dist-info/entry_points.txt
VanityMnem-0.0.2.dist-info/top_level.txt
VanityMnem-0.0.2.dist-info/RECORD
