Metadata-Version: 2.1
Name: VanityMnem
Version: 0.0.2
Summary: create your vanity mnemonics
Home-page: https://github.com/valerio-vaccaro/vanitymnem
Author: Valerio Vaccaro
Author-email: valerio.vaccaro@gmail.com
License: MIT
Classifier: Programming Language :: Python :: 3.7
Classifier: Operating System :: OS Independent
Requires-Python: >=3.7
License-File: LICENSE
Requires-Dist: colorama (==0.4.6)
Requires-Dist: termcolor (==2.4.0)
Requires-Dist: wallycore (==1.2.0)
